dali/__init__.py
dali/address.py
dali/command.py
dali/exceptions.py
dali/frame.py
dali/sequences.py
dali/version.py
dali/device/__init__.py
dali/device/general.py
dali/device/helpers.py
dali/device/light.py
dali/device/occupancy.py
dali/device/pushbutton.py
dali/device/sequences.py
dali/driver/__init__.py
dali/driver/atxled.py
dali/driver/base.py
dali/driver/daliserver.py
dali/driver/hasseb.py
dali/driver/hid.py
dali/driver/serial.py
dali/driver/trace_logging.py
dali/driver/tridonic.py
dali/driver/unipi.py
dali/gear/__init__.py
dali/gear/colour.py
dali/gear/emergency.py
dali/gear/general.py
dali/gear/incandescent.py
dali/gear/led.py
dali/gear/sequences.py
dali/memory/__init__.py
dali/memory/diagnostics.py
dali/memory/energy.py
dali/memory/info.py
dali/memory/location.py
dali/memory/maintenance.py
dali/memory/oem.py
dali/tests/__init__.py
dali/tests/fakes.py
dali/tests/fakes_serial.py
dali/tests/test_colour.py
dali/tests/test_command.py
dali/tests/test_device_sequences.py
dali/tests/test_dummy.py
dali/tests/test_events.py
dali/tests/test_exceptions.py
dali/tests/test_fakes.py
dali/tests/test_frame.py
dali/tests/test_memory.py
dali/tests/test_sequences.py
python_dali-0.11.dist-info/COPYING
python_dali-0.11.dist-info/COPYING.LESSER
python_dali-0.11.dist-info/LICENSE
python_dali-0.11.dist-info/METADATA
python_dali-0.11.dist-info/WHEEL
python_dali-0.11.dist-info/top_level.txt
python_dali-0.11.dist-info/RECORD
