Metadata-Version: 2.1
Name: python-dali
Version: 0.11
Summary: Interface to DALI lighting systems
Home-page: https://github.com/sde1000/python-dali
Author: Stephen Early
Author-email: steve@assorted.org.uk
License: LGPL3+
Platform: UNKNOWN
Classifier: Development Status :: 3 - Alpha
Classifier: Intended Audience :: Developers
Classifier: License :: OSI Approved :: GNU General Public License v3 (GPLv3)
Classifier: License :: OSI Approved :: GNU Lesser General Public License v3 or later (LGPLv3+)
Classifier: Programming Language :: Python :: 3
Requires-Python: >=3.7
License-File: COPYING
License-File: COPYING.LESSER
License-File: LICENSE
Provides-Extra: driver-serial
Requires-Dist: pyserial-asyncio ; extra == 'driver-serial'
Provides-Extra: driver-unipi
Requires-Dist: pymodbus ; extra == 'driver-unipi'
Requires-Dist: pyusb ; extra == 'driver-unipi'
Provides-Extra: test
Requires-Dist: pyserial-asyncio ; extra == 'test'
Requires-Dist: pytest ; extra == 'test'
Requires-Dist: pytest-asyncio ; extra == 'test'
